bst.py
bst-0.5.0.dist-info/LICENSE
bst-0.5.0.dist-info/METADATA
bst-0.5.0.dist-info/WHEEL
bst-0.5.0.dist-info/top_level.txt
bst-0.5.0.dist-info/RECORD
