Metadata-Version: 2.1
Name: bst
Version: 0.5.0
Summary: A binary search tree implemented for learning purposes.
Home-page: https://github.com/rgilbert1/bst
Author: Ryan Gilbert
Author-email: ryangilbert7926@gmail.com
License: MIT
Platform: UNKNOWN
Requires-Python: >=3.6
